
<r>
	<w>	
		<p>ak-</p>
		<b>&#257;barore</b>
		<c></c>
		<t>evil example</t>
		<t>notorious character</t>
	</w>
	<w>	
		<p>kw-</p>
		<b>&#257;b&#299;ra</b>
		<c> (riye) </c>
		<t>to receive in one's hands</t>
		<t>receive</t>
		<t>to take a wife</t>
	</w>
	<w>	
		<p>kw-</p>
		<b>&#257;b&#299;rana</b>
		<c>(nye)</c>
		<t>to marry each other</t>
	</w>
	<w>	
		<p>kw-</p>
		<b>&#257;b&#299;rwa</b>
		<c>(riwe)</c>
		<t>to be married (of woman)</t>
	</w>
	<w>	
		<p>-</p>
		<b>&#257;bo</b>
		<c></c>
		<t>their (poss. adj., poss. pron.) </t>
	</w>
	<w>	
		<p>ic-</p>
		<b>&#257;bona</b>
		<c>(ivy-)</c>
		<t>witness</t>
	</w>
	<w>	
		<p>iny-</p>
		<b>abutongo</b>
		<c>(iny-)</c>
		<t>edible weed (for greens)</t>
	</w>
	<w>	
		<p>-</p>
		<b>&#257;cu</b>
		<c></c>
		<t>our (poss. adj. , poss. pron.)</t>
	</w>
	<w>	
		<p>i-</p>
		<b>w&#257;cu</b>
		<c></c>
		<t>at our place</t>
	</w>
	<w>	
		<p>kw-</p>
		<b>&#257;duka</b>
		<c>(tse)</c>
		<t>to appear suddenly</t>
		<t>come from</t>
		<t>to be new (as e.g. new teaching)</t>
	</w>
	<w>	
		<p>kw-</p>
		<b>&#257;ga</b>
		<c>(ze)</c>
		<t>to be narrow</t>
	</w>
	<w>	
		<p>kw-</p>
		<b>&#257;ga</b>
		<c>(ze)</c>
		<t>to scratch with fingernails</t>
	</w>
	<w>	
		<p>ak-</p>
		<b>&#257;ga</b>
		<c>(no pl.)</c>
		<t>danger</t>
	</w>
	<w>	
		<p>am-</p>
		<b>&#257;gage</b>
		<c></c>
		<t>soft palate</t>
	</w>
	<w>	
		<p>kw-</p>
		<b>&#257;gana</b>
		<c>(nye)</c>
		<t>to scratch each other</t>
	</w>
	<w>	
		<p>umw-</p>
		<b>&#257;gazi</b>
		<c>(imy-)</c>
		<t>lamb,</t>
		<t>kid</t>
	</w>
	<w>	
		<p>ic-</p>
		<b>&#257;gezwe</b>
		<c>(ivy-)</c>
		<t>commandment</t>
	</w>
	<w>	
		<p>kw-</p>
		<b>&#257;gira</b>
		<c>(ye)</c>
		<t>to scratch at, for</t>
	</w>
	<w>	
		<p>kw-</p>
		<b>&#257;giriza</b>
		<c>(je)</c>
		<t>to witness to</t>
		<t>prove</t>
		<t>certify</t>
		<t>accuse</t>
	</w>
	<w>	
		<p>ic-</p>
		<b>&#257;giriza</b>
		<c>(ivy-)</c>
		<t>proof</t>
		<t>evidence</t>
	</w>
	<w>	
		<p>kw-</p>
		<b>&#257;girizwa</b>
		<c>(jwe)</c>
		<t>to be accused</t>
		<t>witnessed against</t>
	</w>
	<w>	
		<p>kw-</p>
		<b>&#257;gisha</b>
		<c>(shije)</c>
		<t>to scratch with</t>
	</w>
	<w>	
		<p>ic-</p>
		<b>&#257;go</b>
		<c>(ivy-)</c>
		<t>trouble</t>
	</w>
	<w>	
		<p>kw-</p>
		<b>&#257;guka</b>
		<c>(tse)</c>
		<t>(from kwaga) to be wide</t>
		<t>to stretch (int.) to have large capacity</t>
	</w>
	<w>	
		<p>kw-</p>
		<b>&#257;gura</b>
		<c>(ye)</c>
		<t>(from kwaga) to stretch (tr.)</t>
	</w>
	<w>	
		<p>kw-</p>
		<b>&#257;gurira</b>
		<c>(ye)</c>
		<t>to enlarge for</t>
	</w>
	<w>	
		<p>kw-</p>
		<b>&#257;gurwa</b>
		<c>(we)</c>
		<t>to be enlarged</t>
	</w>
	<w>	
		<p>kw-</p>
		<b>&#257;gwa</b>
		<c>(zwe)</c>
		<t>to be scratched</t>
	</w>
	<w>	
		<p></p>
		<b>aha</b>
		<c></c>
		<t>here</t>
	</w>
	<w>	
		<p>kw-</p>
		<b>&#257;ha</b>
		<c>(she)</c>
		<t>to gather (from garden)</t>
	</w>
	<w>	
		<p>ic-</p>
		<b>&#257;ha</b>
		<c>(ivy-)</c>
		<t>sin</t>
	</w>
	<w>	
		<p>ukw-</p>
		<b>&#257;ha</b>
		<c>(am-)</c>
		<t>arm-pit</t>
	</w>
	<w>	
		<p>ak-</p>
		<b>&#257;hebge</b>
		<c>(utw-)</c>
		<t>forsaken</t>
		<t>worn out thing</t>
	</w>
	<w>	
		<p>ak-</p>
		<b>&#257;heze</b>
		<c>(no pl.)</c>
		<t>person or thing completely at end of usefulness</t>
	</w>
	<w>	
		<p>kw-</p>
		<b>&#257;hira</b>
		<c>(ye)</c>
		<t>(from kwaha) to cut grass (to use it for something)</t>
	</w>
	<w>	
		<p>kw-</p>
		<b>&#257;hirika</b>
		<c>(tse)</c>
		<t>(from kwaha) to be easy to cut or pull (grass)</t>
	</w>
	<w>	
		<p>kw-</p>
		<b>&#257;hirira</b>
		<c>(ye)</c>
		<t>to cut grass at, for</t>
	</w>
	<w>	
		<p>kw-</p>
		<b>&#257;hiza</b>
		<c>(je)</c>
		<t>to cut grass with</t>
		<t>help to cut</t>
	</w>
	<w>	
		<p></p>
		<b>aho</b>
		<c></c>
		<t>there</t>
		<t>when</t>
		<t>where (not in questions)</t>
		<t>good! (aho rero! that's it!)</t>
		<t>(aho r&#275;ro: That's it!)</t>
	</w>
	<w>	
		<p>kw-</p>
		<b>&#257;huka</b>
		<c>(tse)</c>
		<t>to pasture</t>
		<t>to begin a task</t>
	</w>
	<w>	
		<p>kw-</p>
		<b>&#257;huk&#257;na</b>
		<c>(nye)</c>
		<t>to separate</t>
		<t>divorce (v.i.)</t>
		<t>to finish (v.i.)</t>
	</w>
	<w>	
		<p>kw-</p>
		<b>&#257;huk&#257;nya</b>
		<c>(nije)</c>
		<t>to separate</t>
		<t>divorce</t>
		<t>finish (v.t.)</t>
	</w>
	<w>	
		<p>kw-</p>
		<b>&#257;hura</b>
		<c>(ye)</c>
		<t>to pasture animals in good place</t>
		<t>to put to work</t>
	</w>
	<w>	
		<p>kw-</p>
		<b>&#257;ka</b>
		<c>(tse)</c>
		<t>to take away from</t>
		<t>to demand from</t>
	</w>
	<w>	
		<p>kw-</p>
		<b>&#257;ka</b>
		<c>(tse)</c>
		<t>to shine</t>
	</w>
	<w>	
		<p>umw-</p>
		<b>&#257;ka</b>
		<c>(imy-)</c>
		<t>year</t>
	</w>
	<w>	
		<p>umw-</p>
		<b>ak&#257;ka</b>
		<c>(imy-)</c>
		<t>brass (as used in bracelets)</t>
	</w>
	<w>	
		<p>iny-</p>
		<b>akamwe</b>
		<c>(no pl.)</c>
		<t>one person by himself</t>
	</w>
	<w>	
		<p>ubg-</p>
		<b>&#257;kara</b>
		<c>(am-)</c>
		<t>leafy vegetable (of certain sort)</t>
	</w>
	<w>	
		<p>kw-</p>
		<b>&#257;k&#299;ra</b>
		<c>(riye)</c>
		<t>to receive</t>
		<t>take from another</t>
		<t>to take another's place or burden</t>
	</w>
	<w>	
		<p>kw-</p>
		<b>&#257;k&#299;rana</b>
		<c>(nye)</c>
		<t>to take turns</t>
	</w>
	<w>	
		<p>kw-</p>
		<b>&#257;k&#299;ranwa</b>
		<c>(nywe)</c>
		<t>to take turns</t>
	</w>
	<w>	
		<p>kw-</p>
		<b>&#257;k&#299;rwa</b>
		<c>(we)</c>
		<t>to be received</t>
		<t>taken</t>
	</w>
	<w>	
		<p>kw-</p>
		<b>&#257;k&#299;rwa</b>
		<c>(we)</c>
		<t>to be helped with burden</t>
	</w>
	<w>	
		<p>kw-</p>
		<b>&#257;kura</b>
		<c>(ye)</c>
		<t>to signal to come</t>
	</w>
	<w>	
		<p>kw-</p>
		<b>&#257;ma</b>
		<c>(mye)</c>
		<t>to always or continually do a thing</t>
	</w>
	<w>	
		<p>kw-</p>
		<b>&#257;ma</b>
		<c>(mye)</c>
		<t>to bear fruit</t>
	</w>
	<w>	
		<p>in-</p>
		<b>&#257;ma</b>
		<c>(in-)</c>
		<t>counsel</t>
		<t>council</t>
		<t>advice</t>
	</w>
	<w>	
		<p>iny-</p>
		<b>ama</b>
		<c>(iny-)</c>
		<t>meat</t>
		<t>flesh</t>
	</w>
	<w>	
		<p>kw-</p>
		<b>&#257;maho</b>
		<c>(myeho)</c>
		<t>(from kwama) to be eternal</t>
	</w>
	<w>	
		<p>kw-</p>
		<b>&#257;m&#257;mara</b>
		<c>(ye)</c>
		<t>to become known</t>
		<t>spread everywhere (v.i.)</t>
	</w>
	<w>	
		<p>kw-</p>
		<b>&#257;m&#257;maza</b>
		<c>(je)</c>
		<t>to make known everywhere</t>
	</w>
	<w>	
		<p>kw-</p>
		<b>&#257;ndikwa</b>
		<c>(tswe)</c>
		<t>to be written</t>
	</w>
	<w>	
		<p>umw-</p>
		<b>&#257;ndu</b>
		<c>(imy-)</c>
		<t>inheritance</t>
	</w>
	<w>	
		<p>kw-</p>
		<b>&#257;ndukira</b>
		<c>(ye)</c>
		<t>to be contagious</t>
	</w>
	<w>	
		<p>kw-</p>
		<b>&#257;ndukirwa</b>
		<c>(we)</c>
		<t>to contract a contagious disease</t>
	</w>
	<w>	
		<p>kw-</p>
		<b>&#257;ndukiza</b>
		<c>(je)</c>
		<t>to transmit a contagious disease</t>
	</w>
	<w>	
		<p>kw-</p>
		<b>&#257;ndura</b>
		<c>(ye)</c>
		<t>to catch a disease from another to get dirty</t>
	</w>
	<w>	
		<p>kw-</p>
		<b>&#257;nd&#363;ra</b>
		<c>(ye)</c>
		<t>to take</t>
		<t>to put away</t>
		<t>to gather up</t>
	</w>
	<w>	
		<p>kw-</p>
		<b>&#257;nduruka</b>
		<c>(tse)</c>
		<t>to originate</t>
		<t>to come from</t>
	</w>
	<w>	
		<p>iny-</p>
		<b>&#257;nduruko</b>
		<c>(iny-)</c>
		<t>reason</t>
		<t>origin</t>
		<t>cause</t>
	</w>
	<w>	
		<p>kw-</p>
		<b>&#257;ndurutsa</b>
		<c>(kije)</c>
		<t>to provoke</t>
		<t>start a quarrel</t>
	</w>
	<w>	
		<p>kw-</p>
		<b>&#257;ndurwa</b>
		<c>(we)</c>
		<t>to be contracted (disease)</t>
	</w>
	<w>	
		<p>ic-</p>
		<b>&#257;nga</b>
		<c>(ivy-)</c>
		<t>taste</t>
		<t>flavor</t>
	</w>
	<w>	
		<p>umw-</p>
		<b>&#257;ngange</b>
		<c>(imy-)</c>
		<t>big round red lily (wild)</t>
	</w>
	<w>	
		<p>kw-</p>
		<b>&#257;ng&#257;ra</b>
		<c>(ye)</c>
		<t>to wander about from place to place</t>
	</w>
	<w>	
		<p>urw-</p>
		<b>&#257;ng&#257;ra</b>
		<c>(no pl.)</c>
		<t>carelessness</t>
		<t>negligence</t>
	</w>
	<w>	
		<p>am-</p>
		<b>&#257;ngati</b>
		<c></c>
		<t>belching</t>
		<t>(gutura amangati - to belch)</t>
	</w>
	<w>	
		<p>kw-</p>
		<b>&#257;ng&#257;za</b>
		<c>(je)</c>
		<t>(from kwangara)</t>
		<t>to spread abroad</t>
		<t>make known</t>
	</w>
	<w>	
		<p>umw-</p>
		<b>&#257;ng&#257;zi</b>
		<c>(ab-)</c>
		<t>vagabond</t>
	</w>
	<w>	
		<p>-</p>
		<b>&#257;ngu</b>
		<c>(adj.)</c>
		<t>diluted (esp. milk or beer)</t>
	</w>
	<w>	
		<p>kw-</p>
		<b>&#257;nguha</b>
		<c>(she)</c>
		<t>to lie</t>
	</w>
	<w>	
		<p>kw-</p>
		<b>&#257;nikira</b>
		<c>(ye)</c>
		<t>to put out in sun</t>
	</w>
	<w>	
		<p>kw-</p>
		<b>&#257;n&#299;ra</b>
		<c>(riye)</c>
		<t>to weep</t>
	</w>
	<w>	
		<p>ak-</p>
		<b>&#257;n&#299;ra</b>
		<c>(no pl.)</c>
		<t>whooping cough</t>
	</w>
	<w>	
		<p>kw-</p>
		<b>&#257;nj&#257;njwa</b>
		<c>(jwe)</c>
		<t>to hold lightly</t>
		<t>be careless with</t>
		<t>neglect</t>
	</w>
	<w>	
		<p>-</p>
		<b>&#257;nje</b>
		<c></c>
		<t>my (poss. adj., poss. pron.)</t>
	</w>
	<w>	
		<p>kw-</p>
		<b>&#257;nka</b>
		<c>(nse)</c>
		<t>to refuse</t>
		<t>hate</t>
		<t>resist</t>
		<t>oppose</t>
	</w>
	<w>	
		<p>iny-</p>
		<b>ankamugayo</b>
		<c>(no pl.)</c>
		<t>honesty</t>
		<t>righteousness</t>
		<t>blamelessness</t>
	</w>
	<w>	
		<p>kw-</p>
		<b>&#257;nkana</b>
		<c>(nye)</c>
		<t>to hate each other</t>
	</w>
	<w>	
		<p>kw-</p>
		<b>&#257;nkanya</b>
		<c>(nije)</c>
		<t>to thin out plants</t>
	</w>
	<w>	
		<p>ubg-</p>
		<b>&#257;nkanyi</b>
		<c>(no pl.)</c>
		<t>hatred</t>
	</w>
	<w>	
		<p>umw-</p>
		<b>ankavu</b>
		<c>(ab-)</c>
		<t>child starting to know a little</t>
	</w>
	<w>	
		<p>kw-</p>
		<b>&#257;nkika</b>
		<c>(tse)</c>
		<t>to try repeatedly unsuccessfully</t>
	</w>
	<w>	
		<p>kw-</p>
		<b>&#257;nkira</b>
		<c>(ye)</c>
		<t>to refuse to</t>
		<t>to be impossible for</t>
		<t>to be willful</t>
		<t>disobedient (very strong)</t>
	</w>
	<w>	
		<p>kw-</p>
		<b>&#257;nk&#299;sha</b>
		<c>(shije)</c>
		<t>to cause to hate</t>
	</w>
	<w>	
		<p>urw-</p>
		<b>&#257;nko</b>
		<c>(no pl.)</c>
		<t>hatred</t>
		<t>antipathy</t>
	</w>
	<w>	
		<p>urw-</p>
		<b>&#257;nk&#363;nzi</b>
		<c>(no pl.)</c>
		<t>favoritism</t>
		<t>partiality (sometimes as result of bribe)</t>
	</w>
	<w>	
		<p>kw-</p>
		<b>&#257;nkwa</b>
		<c>(nswe)</c>
		<t>to be hated</t>
	</w>
	<w>	
		<p>umw-</p>
		<b>&#257;nsi</b>
		<c>(ab-)</c>
		<t>enemy</t>
	</w>
	<w>	
		<p>ic-</p>
		<b>ansi</b>
		<c>(ivy-)</c>
		<t>milk cup</t>
	</w>
	<w>	
		<p>ubg-</p>
		<b>&#257;nsi</b>
		<c>(no pl.)</c>
		<t>enmity</t>
	</w>
	<w>	
		<p>kw-</p>
		<b>&#257;nura</b>
		<c>(ye)</c>
		<t>(from kwanikira)</t>
		<t>to bring things in from sun</t>
	</w>
	<w>	
		<p>ubg-</p>
		<b>&#257;nwa</b>
		<c>(no pl.)</c>
		<t>beard</t>
	</w>
	<w>	
		<p>umw-</p>
		<b>&#257;nya</b>
		<c>(imy-)</c>
		<t>time</t>
		<t>space</t>
	</w>
	<w>	
		<p>iny-</p>
		<b>anya</b>
		<c>(iny-)</c>
		<t>see i-nyanya</t>
	</w>
	<w>	
		<p>ic-</p>
		<b>&#257;nya</b>
		<c>(ivy-)</c>
		<t>place surrounding great chief's kraal</t>
		<t>good pastures</t>
	</w>
	<w>	
		<p>-</p>
		<b>&#257;nyu</b>
		<c></c>
		<t>your (pl.) (poss. adj., pron.)</t>
	</w>
	<w>	
		<p>kw-</p>
		<b>&#257;nzika</b>
		<c>(tse)</c>
		<t>to start</t>
	</w>
	<w>	
		<p>ic-</p>
		<b>&#257;nzo</b>
		<c>(ivy-)</c>
		<t>small opening in enclosure</t>
	</w>
	<w>	
		<p>umw-</p>
		<b>anza</b>
		<c>(imy-)</c>
		<t>track of animal</t>
	</w>
	<w>	
		<p>urw-</p>
		<b>&#257;ra</b>
		<c>(inz-)</c>
		<t>fingernail</t>
		<t>toenail</t>
		<t>claw</t>
	</w>
	<w>	
		<p>inz-</p>
		<b>ara</b>
		<c>(inz-)</c>
		<t>see in-zara</t>
	</w>
	<w>	
		<p>ak-</p>
		<b>&#257;r&#257;nda</b>
		<c>(no pl.)</c>
		<t>ancient customs</t>
	</w>
	<w>	
		<p>ubg-</p>
		<b>&#257;r&#257;ra</b>
		<c>(no pl.)</c>
		<t>contagious disease (term of scorn: uri n'ubgarara)</t>
	</w>
	<w>	
		<p>ic-</p>
		<b>&#257;ri</b>
		<c>(ivy-)</c>
		<t>nest</t>
	</w>
	<w>	
		<p>kw-</p>
		<b>&#257;rika</b>
		<c>(tse)</c>
		<t>to make a nest</t>
	</w>
	<w>	
		<p></p>
		<b>ariko</b>
		<c></c>
		<t>but</t>
	</w>
	<w>	
		<p>umw-</p>
		<b>&#257;rimu</b>
		<c>(ab-)</c>
		<t>teacher</t>
	</w>
	<w>	
		<p>ic-</p>
		<b>&#257;rimwe</b>
		<c>(no pl.)</c>
		<t>all together</t>
		<t>in unison</t>
	</w>
	<w>	
		<p>ak-</p>
		<b>&#257;r&#333;nda</b>
		<c>(no pl.)</c>
		<t>inherited property or position</t>
		<t>origin</t>
	</w>
	<w>	
		<p>kw-</p>
		<b>&#257;ruka</b>
		<c>(tse)</c>
		<t>reach the age of accountability</t>
		<t>to grow</t>
	</w>
	<w>	
		<p>kw-</p>
		<b>&#257;rura</b>
		<c>(ye)</c>
		<t>to dish up food</t>
	</w>
	<w>	
		<p>kw-</p>
		<b>&#257;r&#363;za</b>
		<c>(je)</c>
		<t>to tear down nest</t>
	</w>
	<w>	
		<p>urw-</p>
		<b>&#257;rwa</b>
		<c></c>
		<t>(or, urwagwa) banana beer</t>
	</w>
	<w>	
		<p>urw-</p>
		<b>asakusaku</b>
		<c>(in-)</c>
		<t>chin</t>
	</w>
	<w>	
		<p>kw-</p>
		<b>&#257;sama</b>
		<c>(mye)</c>
		<t>to open one's mouth</t>
	</w>
	<w>	
		<p>kw-</p>
		<b>&#257;samika</b>
		<c>(tse)</c>
		<t>to cause to open the mouth</t>
	</w>
	<w>	
		<p>kw-</p>
		<b>&#257;samura</b>
		<c>(ye)</c>
		<t>to sneeze</t>
	</w>
	<w>	
		<p>kw-</p>
		<b>&#257;samuza</b>
		<c>(je)</c>
		<t>cause to sneeze</t>
	</w>
	<w>	
		<p>kw-</p>
		<b>&#257;sana</b>
		<c>(nye)</c>
		<t>to clash together</t>
		<t>make big noise</t>
	</w>
	<w>	
		<p>kw-</p>
		<b>&#257;tagura</b>
		<c>(ye)</c>
		<t>to tell the whole truth without hiding a thing</t>
	</w>
	<w>	
		<p>kw-</p>
		<b>&#257;t&#299;ra</b>
		<c>(riye)</c>
		<t>to go down the middle (e.g. of path or country)</t>
	</w>
	<w>	
		<p>kw-</p>
		<b>&#257;tira</b>
		<c>(ye)</c>
		<t>to choose leader, , , </t>
		<t>to put bees in new hive</t>
		<t>to dedicate</t>
		<t>ordain</t>
	</w>
	<w>	
		<p>kw-</p>
		<b>&#257;t&#299;ra</b>
		<c>(riye)</c>
		<t>to crack (v.t. and v.i.)</t>
	</w>
	<w>	
		<p>kw-</p>
		<b>&#257;t&#299;ra</b>
		<c>(ye)</c>
		<t>to gulp down water</t>
	</w>
	<w>	
		<p>urw-</p>
		<b>&#257;to</b>
		<c>(inz-)</c>
		<t>cup</t>
	</w>
	<w>	
		<p>ubg-</p>
		<b>&#257;to</b>
		<c>(am-)</c>
		<t>boat</t>
	</w>
	<w>	
		<p>kw-</p>
		<b>&#257;tsa</b>
		<c>(kije)</c>
		<t>(from kwaka) to blow the fire</t>
	</w>
	<w>	
		<p>ubg-</p>
		<b>&#257;tsi</b>
		<c>(no pl.)</c>
		<t>grass (esp. for building)</t>
		<t>field</t>
	</w>
	<w>	
		<p>ivy-</p>
		<b>&#257;tsi</b>
		<c></c>
		<t>(sing. rare icatsi) grass of any kind</t>
	</w>
	<w>	
		<p>ak-</p>
		<b>&#257;tsi</b>
		<c>gatoto</c>
		<t>green</t>
	</w>
	<w>	
		<p>kw-</p>
		<b>&#257;tura</b>
		<c>(ye)</c>
		<t>to make known</t>
		<t>bring into open from hidden place</t>
		<t>confess</t>
		<t>to pronounce clearly</t>
		<t>to open (flower)</t>
	</w>
	<w>	
		<p>kw-</p>
		<b>&#257;turuka</b>
		<c>(tse)</c>
		<t>to crack</t>
		<t>to open (v.i.)</t>
	</w>
	<w>	
		<p>kw-</p>
		<b>&#257;turura</b>
		<c>(ye)</c>
		<t>to burst open (v.t.)</t>
	</w>
	<w>	
		<p>umw-</p>
		<b>&#257;vu</b>
		<c>(imy-)</c>
		<t>discarded things</t>
		<t>trash</t>
		<t>garbage</t>
	</w>
	<w>	
		<p>kw-</p>
		<b>av&#363;ra</b>
		<c>(ye)</c>
		<t>to crawl</t>
		<t>creep (on hands and knees)</t>
	</w>
	<w>	
		<p>urw-</p>
		<b>&#257;vya</b>
		<c>(inz-)</c>
		<t>small pot (for butter)</t>
	</w>
	<w>	
		<p>-</p>
		<b>&#257;we</b>
		<c></c>
		<t>your (s.) (poss. adj., pron.)</t>
	</w>
	<w>	
		<p>kw-</p>
		<b>&#257;ya</b>
		<c>(ye)</c>
		<t>to waste</t>
		<t>consume uselessly</t>
	</w>
	<w>	
		<p>ic-</p>
		<b>&#257;yi</b>
		<c>(no pl.)</c>
		<t>tea</t>
	</w>
	<w>	
		<p>kw-</p>
		<b>&#257;yura</b>
		<c>(ye)</c>
		<t>to yawn</t>
	</w>
	<w>	
		<p>kw-</p>
		<b>&#257;za</b>
		<c>(gije)</c>
		<t>to make narrow</t>
	</w>
	<w>	
		<p>kw-</p>
		<b>&#257;zwa</b>
		<c>(gijwe)</c>
		<t>to be made narrow</t>
	</w>
</r>